pyamlconf/__init__.py
pyamlconf/config.py
pyamlconf-0.0.4.dist-info/METADATA
pyamlconf-0.0.4.dist-info/WHEEL
pyamlconf-0.0.4.dist-info/top_level.txt
pyamlconf-0.0.4.dist-info/RECORD
