Metadata-Version: 2.4
Name: pyamlconf
Version: 0.0.4
Summary: A simple YAML-based configuration loader for Python
Author-email: Monster Yao <yymmiinngg@163.com>
License: MIT
Project-URL: Homepage, https://github.com/yymmiinngg/pyamlconf
Requires-Python: >=3.9
Requires-Dist: pyyaml
